flask_snow
