Metadata-Version: 1.2
Name: flask-snow
Version: 0.2.8
Summary: Pysnow extension for Flask
Home-page: https://github.com/rbw0/flask-snow
Author: Robert Wikman
Author-email: rbw@vault13.org
Maintainer: Robert Wikman
Maintainer-email: rbw@vault13.org
License: MIT
Download-URL: https://github.com/rbw0/flask-snow/tarball/0.2.8
Platform: any
Classifier: Environment :: Web Environment
Classifier: Intended Audience :: Developers
Classifier: License :: OSI Approved :: BSD License
Classifier: Operating System :: OS Independent
Classifier: Programming Language :: Python
Classifier: Topic :: Internet :: WWW/HTTP :: Dynamic Content
Classifier: Topic :: Software Development :: Libraries :: Python Modules
